{
  "data": {
    "talk": {
      "abstract": "In high school science, we're taught to always include units in equations. Why not in scientific Python code? I'll show why and how to keep track of units in Python using real-world examples.", 
      "bio": "", 
      "conf_key": 19, 
      "conf_url": "http://2012.pycon.ca/talk/19", 
      "description": "In high school science, we're taught to always include units in equations. Why not in scientific Python code? I'll show why and how to keep track of units in Python using real-world examples.", 
      "duration": 20, 
      "end": "2012-11-10T10:45:00-05:00", 
      "id": 19, 
      "level": "novice", 
      "name": "Writing self-documenting scientific code using physical quantities", 
      "owner_id": 33, 
      "room": "Lower hall", 
      "schedule_code": "A1", 
      "schedule_slot_id": 3, 
      "speaker_first_name": "Trevor", 
      "speaker_last_name": "Bekolay", 
      "start": "2012-11-10T10:25:00-05:00", 
      "title": "Writing self-documenting scientific code using physical quantities", 
      "type": "talk", 
      "video_release": true
    }
  }, 
  "errors": []
}